ws_cli_chat/__init__.py
ws_cli_chat/ascii_arts.py
ws_cli_chat/cli_chat.py
ws_cli_chat/code_window.py
ws_cli_chat/comands.py
ws_cli_chat/myconsole.py
ws_cli_chat/render.py
ws_cli_chat-0.4.4.dist-info/entry_points.txt
ws_cli_chat-0.4.4.dist-info/METADATA
ws_cli_chat-0.4.4.dist-info/WHEEL
ws_cli_chat-0.4.4.dist-info/RECORD
