Metadata-Version: 2.1
Name: ws-cli-chat
Version: 0.4.4
Summary: simple cli-websocket chat
Author: __coelho__
Author-email: 109885900+MikalROn@users.noreply.github.com
Requires-Python: >=3.10,<4.0
Classifier: Programming Language :: Python :: 3
Classifier: Programming Language :: Python :: 3.10
Classifier: Programming Language :: Python :: 3.11
Requires-Dist: colorama (>=0.4.6,<0.5.0)
Requires-Dist: eventsimplegui (>=0.3.0,<0.4.0)
Requires-Dist: pysimplegui (>=4.60.4,<5.0.0)
Requires-Dist: tk (>=0.1.0,<0.2.0)
Requires-Dist: typer[all] (>=0.7.0,<0.8.0)
Requires-Dist: websockets (>=11.0.2,<12.0.0)
